{"v":"4.8.0","meta":{"g":"LottieFiles AE ","a":"","k":"","d":"","tc":""},"fr":25,"ip":0,"op":80,"w":1080,"h":1080,"nm":"MAN","ddd":0,"assets":[],"layers":[{"ddd":0,"ind":1,"ty":4,"nm":"Man","sr":1,"ks":{"o":{"a":0,"k":100,"ix":11},"r":{"a":0,"k":0,"ix":10},"p":{"a":0,"k":[539.873,542.277,0],"ix":2},"a":{"a":0,"k":[0,0,0],"ix":1},"s":{"a":0,"k":[197,197,100],"ix":6}},"ao":0,"shapes":[{"ind":0,"ty":"sh","ix":1,"ks":{"a":0,"k":{"i":[[0,0],[-132.238,1.069],[10.693,94.099],[85.901,1.069],[-1.069,-85.901],[-91.218,4.13],[3.208,-128.673]],"o":[[0,0],[0,0],[0,0],[0,0],[0,0],[0,0],[0,0]],"v":[[-146.954,156.762],[-3.015,14.255],[87.057,-81.089],[-4.547,-157.01],[-86.171,-65.406],[8.785,14.071],[147.651,157.01]],"c":false},"ix":2},"nm":"Path 1","mn":"ADBE Vector Shape - Group","hd":false},{"ty":"tm","s":{"a":1,"k":[{"i":{"x":[0],"y":[0.971]},"o":{"x":[0.333],"y":[0]},"t":0,"s":[0]},{"t":25,"s":[100]}],"ix":1},"e":{"a":1,"k":[{"i":{"x":[0],"y":[1]},"o":{"x":[0.333],"y":[0]},"t":50,"s":[0]},{"t":75,"s":[100]}],"ix":2},"o":{"a":0,"k":0,"ix":3},"m":1,"ix":2,"nm":"Trim Paths 1","mn":"ADBE Vector Filter - Trim","hd":false},{"ty":"st","c":{"a":0,"k":[1,0,0,1],"ix":3},"o":{"a":0,"k":100,"ix":4},"w":{"a":0,"k":20,"ix":5},"lc":2,"lj":1,"ml":10,"bm":0,"nm":"Stroke 1","mn":"ADBE Vector Graphic - Stroke","hd":false}],"ip":0,"op":80,"st":0,"bm":0}],"markers":[]}